LICENSE
MANIFEST.in
README.md
pyproject.toml
setup.py
rsalor/__init__.py
rsalor/cli.py
rsalor/msa.py
rsalor/rsa/__init__.py
rsalor/rsa/rsa_biopython.py
rsalor/rsa/rsa_dssp.py
rsalor/rsa/rsa_music.py
rsalor/rsa/rsa_solver.py
rsalor/sequence/__init__.py
rsalor/sequence/amino_acid.py
rsalor/sequence/fasta_reader.py
rsalor/sequence/mutation.py
rsalor/sequence/pairwise_alignment.py
rsalor/sequence/sequence.py
rsalor/structure/__init__.py
rsalor/structure/residue.py
rsalor/structure/structure.py
rsalor/utils/CSV.py
rsalor/utils/__init__.py
rsalor/utils/ali_to_fasta.py
rsalor/utils/logger.py
rsalor/utils/utils.py
rsalor/weights/__init__.py
rsalor/weights/computeWeightsBackend.cpp
rsalor/weights/compute_weights.py
rsalor/weights/msa.cpp
rsalor/weights/build/CMakeFiles/3.22.1/CompilerIdCXX/CMakeCXXCompilerId.cpp
rsalor/weights/include/msa.h