Metadata-Version: 2.4
Name: rsalor
Version: 1.1.9
Summary: Combines structural data (Relative Solvent Accessibility, RSA) and evolutionary data (Log Odd Ratio, LOR from MSA) to evaluate missense mutations in proteins.
Author-email: Matsvei Tsishyn <matsvei.tsishyn@protonmail.com>
License-Expression: MIT
Project-URL: Homepage, https://github.com/3BioCompBio/RSALOR
Classifier: Programming Language :: Python :: 3
Classifier: Programming Language :: C++
Classifier: Programming Language :: C
Classifier: Operating System :: OS Independent
Classifier: Topic :: Scientific/Engineering :: Bio-Informatics
Requires-Python: >=3.9
License-File: LICENSE
Requires-Dist: numpy
Requires-Dist: biopython>=1.75
Dynamic: license-file
